img2text.py
py.typed
img2text-0.1.1.dist-info/METADATA
img2text-0.1.1.dist-info/WHEEL
img2text-0.1.1.dist-info/entry_points.txt
img2text-0.1.1.dist-info/licenses/LICENSE
img2text-0.1.1.dist-info/RECORD
