Metadata-Version: 2.1
Name: img2text
Version: 0.1.1
Summary: A lightweight module to generate colorful ascii art from images
Project-URL: Repository, https://github.com/hmiladhia/img2text.git
Project-URL: Issues, https://github.com/hmiladhia/img2text/issues
Author-email: Dhia Hmila <dhiahmila.dev@gmail.com>
Maintainer-email: Dhia Hmila <dhiahmila.dev@gmail.com>
License: MIT License
License-File: LICENSE
Keywords: art,ascii,ascii-art,color,colour,image,text
Classifier: Development Status :: 5 - Production/Stable
Classifier: License :: OSI Approved :: MIT License
Classifier: Operating System :: OS Independent
Classifier: Programming Language :: Python :: 3
Requires-Python: >=3.7
Requires-Dist: colorama>=0.4
Requires-Dist: pillow>=8.2.0
